{
    "no_wrap": true,
    "text_block_list": [
        {
            "text": "Mayano Top Gun showed a glimpse of her tremendous \nability in the Selection Race."
        },
        {
            "text": "I'm looking around the school to see her again……"
        },
        {
            "name": "Mayano Top Gun",
            "text": "Yukippe, hurry up, hurry up～! Don't you wanna \ngo watch City run? Come on, let's go!"
        },
        {
            "name": "Yukino Bijin",
            "text": "Wait a minute, Maya! A country girl like me shouldn't go to \nsuch a crowded place……!"
        },
        {
            "name": "Mayano Top Gun",
            "text": "Geez, it's okay! \nLook, Maya will stay with you……"
        },
        {
            "name": "Mayano Top Gun",
            "text": "Oh? Could you be―"
        },
        {
            "name": "Mayano Top Gun",
            "text": "I knew it! You're the person I met at the Selection Race! Wow, we \nmeet again! What are you doing here?",
            "choice_data_list": [
                "I came looking for you.",
                "I came looking for you."
            ]
        },
        {
            "name": "Mayano Top Gun",
            "text": "Huh? for Maya? \nWow…… something like this―"
        },
        {
            "name": "Mayano Top Gun",
            "text": "Is like an adult situation～!! Kya～～～♪"
        },
        {
            "name": "Mayano Top Gun",
            "text": "But but, Maya is in a hurry right now. \nI'd love to chat with you, but… umm……"
        },
        {
            "name": "Mayano Top Gun",
            "text": "Oh, yeah! You should come with us! \nYou're fine with that right, Yukippe?"
        },
        {
            "name": "Yukino Bijin",
            "text": "Huh? What, uh? \nMaya, what do you mean……"
        },
        {
            "name": "Mayano Top Gun",
            "text": "It's decided! \nIn that case, TAKE-OFF!!"
        },
        {
            "name": "Yukino Bijin",
            "text": "Uhyaa!?"
        },
        {
            "text": "Together with Yukino Bijin, \nwe were taken and headed towards an unknown destination―"
        },
        {
            "name": "Commentator",
            "text": "Here we are at the fourth turn! Gold City, coming from the \noutside! Tamamo Cross, chasing hard from behind!"
        },
        {
            "name": "Tamamo Cross",
            "text": "I'll show you my guts!"
        },
        {
            "name": "Gold City",
            "text": "Like hell I'll let you……!!!!"
        },
        {
            "name": "Yukino Bijin",
            "text": "Wow, wow……! City-san, she's amazing……!"
        },
        {
            "name": "Mayano Top Gun",
            "text": "Yeah-yeah, City-san and Tamamo-san \nthey're both sparkling!"
        },
        {
            "name": "Mayano Top Gun",
            "text": "I see… so you could go 'byuun' over \nthere. Maya, didn't know that……!"
        },
        {
            "name": "Mayano Top Gun",
            "text": "The race of adult Uma Musume is exciting……!"
        },
        {
            "text": "Mayano Top Gun watched the race from start to finish \nwith her twinkling eyes, as the top Uma Musume \nwere competing against each other……"
        },
        {
            "name": "Commentator",
            "text": "Goal in! The winner of the race is TAMAMO CROSS! A close second \nplace goes to Gold City!"
        },
        {
            "name": "Tamamo Cross",
            "text": "Ha, ha, ha…… \nAlright!! I won!!"
        },
        {
            "name": "Gold City",
            "text": "Ah damn it, I missed the timing of the sprint……"
        },
        {
            "name": "Gold City",
            "text": "But that won't happen next time. I'll \ncatch up with you, Tamamo-senpai."
        },
        {
            "name": "Tamamo Cross",
            "text": "Heh heh, whenever you want, City! I'll take you anytime!"
        },
        {
            "name": "Yukino Bijin",
            "text": "Wow, that was an awesome race……! \nTamamo-san and City-san were so cool… ……!"
        },
        {
            "name": "Mayano Top Gun",
            "text": "I see, it was too early to go 'dan' there……! \nCity-san understood that, amazing……!"
        },
        {
            "name": "Mayano Top Gun",
            "text": "Ugh～, The girls in these exciting races are so \nsparkly!! How nice… Maya wants to shine too……!",
            "choice_data_list": [
                "Excitement? Sparkling?"
            ]
        },
        {
            "name": "Mayano Top Gun",
            "text": "Yeah! There are so many things that Maya doesn't know about big \nraces like this, it's so exciting!"
        },
        {
            "name": "Mayano Top Gun",
            "text": "Adult Uma Musume who understand what Maya \ndoesn't understand look so sparkling～!"
        },
        {
            "name": "Mayano Top Gun",
            "text": "That's why, Maya also want to be like them! \nI want to shine in exciting races!"
        },
        {
            "name": "Mayano Top Gun",
            "text": "Sigh… Must be nice… Twinkle Series…… \nMaya can't wait to run there too～……!"
        },
        {
            "name": "Yukino Bijin",
            "text": "Ah, me too……! G1 may still be a distant stage, \nbut someday I will definitely…!"
        },
        {
            "name": "Yukino Bijin",
            "text": "Alright, let's get back to school \nand start training!!"
        },
        {
            "name": "Mayano Top Gun",
            "text": "Eh-, training……?"
        },
        {
            "name": "Mayano Top Gun",
            "text": "No! Maya won't do it. \nIt's boring."
        },
        {
            "name": "Mayano Top Gun",
            "text": "I'm off to explore the racetrack. \nBye!!"
        },
        {
            "name": "Yukino Bijin",
            "text": "Huh, Maya!? Ah～ there she goes……",
            "choice_data_list": [
                "Is she not good at training?",
                "Is that girl bad at training?"
            ]
        },
        {
            "name": "Yukino Bijin",
            "text": "No-no! There is probably nothing that Maya is not good at. \nShe's an amazing girl who can do anything she puts her mind to!"
        },
        {
            "name": "Yukino Bijin",
            "text": "She got the hang of running on dirt on her first try, and I've \nnever seen her struggle in the dance lessons for the Winning Live."
        },
        {
            "name": "Yukino Bijin",
            "text": "She's also good at studying…… Anyway, \nMaya is amazing when she \"gets it\"!",
            "choice_data_list": [
                "'Gets it'?"
            ]
        },
        {
            "name": "Yukino Bijin",
            "text": "Yes, Maya often says that. No matter what it is, if she says \n'I got it' she'll be good at it!"
        },
        {
            "text": "Thanks to Yukino Bizin, I was able to find out a little more \nabout what Mayano Top Gun was capable of."
        },
        {
            "text": "Apparently she has a natural ability to 'get it'―"
        },
        {
            "text": "In other words, it seems that she was born \nwith amazing intuition that allows her to find \nthe 'right answer'……!"
        },
        {
            "name": "Yukino Bijin",
            "text": "But for some reason, the training seems to be uninteresting to \nher…… I heard that she hasn't participated in any of the \ntrainings since the first one.",
            "choice_data_list": [
                "She only trained once!?",
                "She only trained once!?"
            ]
        },
        {
            "name": "Yukino Bijin",
            "text": "Yes, ……but because of that, \nshe got banned from all races, \nincluding simulations."
        },
        {
            "name": "Yukino Bijin",
            "text": "I understand that a race is a place to show the results of your \ntraining, but…… I feel a little sorry for Maya……"
        },
        {
            "text": "The image of Mayano Top Gun \nwanting to race so badly flashes through my mind……"
        },
        {
            "text": "Can I do something about it……?"
        }
    ]
}