{
    "no_wrap": true,
    "text_block_list": [
        {
            "name": "Ines Fujin",
            "text": "<i>Haa, haah, haa……! \n</i>Finally done with beach running～"
        },
        {
            "text": "The annual summer training camp had begun. \nI hoped to gain a burst of improvement here to \ntake into races, however —"
        },
        {
            "name": "Beach Bar Owner",
            "text": "…… Lil' Ines? It really is, knew I recognized you!"
        },
        {
            "name": "Ines Fujin",
            "text": "<i>Hueeh!?</i> \nIs that you, Mister Beach?!",
            "choice_data_list": [
                "Someone you know?"
            ]
        },
        {
            "name": "Ines Fujin",
            "text": "Yeah! He often helped me out back home! \nI heard he'd moved, but I never thought I'd find him here……!"
        },
        {
            "name": "Beach Bar Owner",
            "text": "That's what I wanna say! I knew you attended Tracen Academy \nbut to think I'd see you again like this～"
        },
        {
            "name": "Beach Bar Owner",
            "text": "I'm running a beach bar here nowdays. \nDo come drop by later if you got time!"
        },
        {
            "name": "Ines Fujin",
            "text": "For sure! We'll be there!"
        },
        {
            "text": "After training, we made good on the invitation \nand headed to the beach bar, but —"
        },
        {
            "name": "Ines Fujin",
            "text": "Hmmm. It looks super duper busy……"
        },
        {
            "name": "Beach Bar Owner",
            "text": "Oh, lil' Ines! Sorry I don't got much time for yeh now～"
        },
        {
            "name": "Beach Bar Owner",
            "text": "It's ain't like this most days, but when the summer festival \nrolls 'round there's always a big increase in customers…"
        },
        {
            "name": "Ines Fujin",
            "text": "Makes sense～……",
            "choice_data_list": [
                "You're thinking of helping."
            ]
        },
        {
            "name": "Ines Fujin",
            "text": "Ahaha, you got me."
        },
        {
            "name": "Ines Fujin",
            "text": "I'll make sure it doesn't affect my training, so can I —"
        },
        {
            "name": "Ines Fujin",
            "text": "…………"
        },
        {
            "name": "Ines Fujin",
            "text": "Actually, I want you to come with me! Please!"
        },
        {
            "name": "Ines Fujin",
            "text": "Here you go! Two large yakisoba!"
        },
        {
            "name": "Ines Fujin",
            "text": "I have your grilled carrot and tropical drink right here. Enjoy～!"
        },
        {
            "name": "Man A",
            "text": "Excuse me! I'd like to order!",
            "choice_data_list": [
                "C-Coming!"
            ]
        },
        {
            "name": "Young Woman A",
            "text": "Where's the Blue Hawaii I ordered?",
            "choice_data_list": [
                "I'm sorry! Just a minute please!"
            ]
        },
        {
            "name": "Beach Bar Owner",
            "text": "You good, kid? It don't look like you got \na lot of experience doing this……"
        },
        {
            "name": "Beach Bar Owner",
            "text": "You alright there? It don't look like you got \na lot of experience doing this……"
        },
        {
            "name": "Ines Fujin",
            "text": "Don't worry! I know you're starting to, but give it a bit."
        },
        {
            "name": "Ines Fujin",
            "text": "It might not be immediately clear, \nbut my trainer can be quite reliable♪",
            "choice_data_list": [
                "(Ines……!)"
            ]
        },
        {
            "text": "I thought to myself that I had to live up to her expectations \nno matter what and returned direction kitchen."
        },
        {
            "text": "By the time of the summer festival —",
            "choice_data_list": [
                "Here you go, one ramen set!"
            ]
        },
        {
            "name": "Young Woman B",
            "text": "Whoa, already? \nThank you～!"
        },
        {
            "name": "Young Woman B",
            "text": "Whoa, already? \nThank you～!"
        },
        {
            "name": "Beach Bar Owner",
            "text": "Hoowee～ I wasn't sure at first but you really grew into this!"
        },
        {
            "name": "Ines Fujin",
            "text": "Ehehe, I told you so♪"
        },
        {
            "name": "Beach Bar Owner",
            "text": "It's been a big help having you both here. \nThe crowds have calmed a bit now so why \ndon't the two of you head off to the festival!"
        },
        {
            "name": "Ines Fujin",
            "text": "Okay! Let's go, Trainer!"
        },
        {
            "name": "Ines Fujin",
            "text": "Mmmm～! I love having a honey drink after work～♪",
            "choice_data_list": [
                "Good work, Ines."
            ]
        },
        {
            "name": "Ines Fujin",
            "text": "You too♪ \nThanks for coming with me!",
            "choice_data_list": [
                "I thought you were about to run \noff to help on your own at first."
            ]
        },
        {
            "name": "Ines Fujin",
            "text": "Mmm. I think I would have, before."
        },
        {
            "name": "Ines Fujin",
            "text": "You always seemed kind of a klutz and in need of help \nmore often than helping, you know?",
            "choice_data_list": [
                "R-Really…"
            ]
        },
        {
            "name": "Ines Fujin",
            "text": "Ahaha! But that's not so much the case anymore."
        },
        {
            "name": "Ines Fujin",
            "text": "You don't always look it, but I know you're someone \nwho can do it when you put your mind to it, Trainer!"
        },
        {
            "name": "Ines Fujin",
            "text": "That's why I felt I could rely on you a little today. \nWasn't wrong, was I?",
            "choice_data_list": [
                "You bet!"
            ]
        },
        {
            "name": "Ines Fujin",
            "text": "Aah, and you were so unreliable when we first met～ \nReally, where's all that gone?",
            "choice_data_list": [
                "I want you to be able to count on me, \nand run to your heart's content."
            ]
        },
        {
            "name": "Ines Fujin",
            "text": "<i>! \n</i>"
        },
        {
            "name": "Ines Fujin",
            "text": "I see……"
        },
        {
            "name": "Ines Fujin",
            "text": "Oh what a siiight! \nThere's fireworks all over the sky!",
            "choice_data_list": [
                "It's beautiful.",
                "It's beautiful."
            ]
        },
        {
            "name": "Ines Fujin",
            "text": "Yeah!"
        },
        {
            "name": "Ines Fujin",
            "text": "But you know… if I had to do everything alone… \nI think I'd have been too busy to pay attention to \nsummer festivals and fireworks."
        },
        {
            "name": "Ines Fujin",
            "text": "Maybe summer festivals are fun and the fireworks so \nbeautiful because of a certain someone, hmm?",
            "choice_data_list": [
                "Ines……"
            ]
        },
        {
            "name": "Ines Fujin",
            "text": "Trainer, I —"
        },
        {
            "name": "Ines Fujin",
            "text": "I'm glad I enrolled at the academy. I'm glad I could \ncome to summer camp. ……I'm glad I met you!"
        },
        {
            "name": "Bandaged Up Horsegirl",
            "text": "If I'd known… I don't want it to end like this…… \nI wish I'd never met you……!"
        },
        {
            "name": "Ines Fujin",
            "text": "…… Trainer?",
            "choice_data_list": [
                "It's nothing…… Thanks."
            ]
        },
        {
            "name": "Ines Fujin",
            "text": "Maan, look at your face! \nIf you're happy then smile, smile!"
        },
        {
            "text": "Glad she met me… Having been told that, I need \nto become a more reliable trainer, for her.",
            "choice_data_list": [
                "Yeah! I'll keep working hard for yoy —",
                "Yeah! I'll keep working hard for yoy —"
            ]
        },
        {
            "name": "Ines Fujin",
            "text": "<i>Pffft! \n</i>"
        },
        {
            "name": "Ines Fujin",
            "text": "<i>Maaaan～!</i> You have to be cool the whole way \nthrough if you're gonna say stuff like that!"
        },
        {
            "name": "Ines Fujin",
            "text": "I'll keep counting on you, Trainer♪"
        },
        {
            "text": "There's a mischievous smile on Ines Fujin's face, \nbut her eyes are full of warmth."
        }
    ]
}