{
    "no_wrap": true,
    "text_block_list": [
        {
            "text": "On a holiday, I was taking a walk at the \npark when a voice called out to me."
        },
        {
            "text": "Oh, Trainer-san.",
            "name": "Grass Wonder"
        },
        {
            "text": "Bumping in to you here is quite a coincidence, isn't it?～",
            "name": "Grass Wonder",
            "choice_data_list": [
                "What are you doing?",
                "What are you doing?"
            ]
        },
        {
            "text": "Just wandering here and there aimlessly……you could call it a \nwalk. I tend to spend most of my days off like this, you know?",
            "name": "Grass Wonder"
        },
        {
            "text": "My friends often tell me that I'm wasting a lot \nof time but, since I came from America, just walking \nand seeing the scenery is fulfilling.",
            "name": "Grass Wonder"
        },
        {
            "text": "Besides, even if it's a day off, I still want \nto move my body even just a little bit.",
            "name": "Grass Wonder"
        },
        {
            "text": "While I'm moving my body, I can enjoy the atmosphere \nof this country…… you could say walking is a form \nof entertainment for me, you know?～",
            "name": "Grass Wonder"
        },
        {
            "text": "But well, I've already seen all around this area, \nso I'm not sure where I should go next time.",
            "name": "Grass Wonder",
            "choice_data_list": [
                "I could act as your guide"
            ]
        },
        {
            "text": "Eh, to a place for a walk? \nI see, that's a good idea～",
            "name": "Grass Wonder"
        },
        {
            "text": "Maybe Trainer-san knows some scenery that \nI've never seen before, after all.",
            "name": "Grass Wonder"
        },
        {
            "text": "Fufu, in that case, I'll take you up on that offer. \nLet's take a leisurely stroll together!",
            "name": "Grass Wonder"
        },
        {
            "text": "So I chose a few places that Grass \nWonder might not have known about."
        },
        {
            "text": "To think there was a teahouse here. \nI never knew～.",
            "name": "Grass Wonder"
        },
        {
            "text": "Even with all these fancy shops lined up, \nthey haven't forgotten to give it a well balanced feel.",
            "name": "Grass Wonder"
        },
        {
            "text": "Oh, they've even created such a \nlarge menu using my favorite matcha♪",
            "name": "Grass Wonder"
        },
        {
            "text": "……But, it might have been a mistake learning about \nthis place. The temptation of sweets…… hmmmmm～……",
            "name": "Grass Wonder"
        },
        {
            "text": "And like that, I visited several places \ntogether with Grass Wonder―"
        },
        {
            "text": "A nice, quiet walk is good, but a fun walk like this is good too, \nisn't it? It's the result of walking together.",
            "name": "Grass Wonder"
        },
        {
            "text": "Trainer-san, where should we go next??",
            "name": "Grass Wonder"
        },
        {
            "text": "When Grass Wonder asked, I looked around. \nThe Game Center caught my eye.",
            "choice_data_list": [
                "Want to see the Game Center?"
            ]
        },
        {
            "text": "The Game Center, is it……? \nHmmmmm～, I'm not too familiar with places like that……",
            "name": "Grass Wonder"
        },
        {
            "text": "When it comes to walks, I can't help but think that \na leisurely stroll is more suited for a quieter place……",
            "name": "Grass Wonder",
            "choice_data_list": [
                "You might discover something new"
            ]
        },
        {
            "text": "A new discovery……",
            "name": "Grass Wonder"
        },
        {
            "text": "That's true, every place we've seen up until now had \nseveral new discoveries to be made as well.",
            "name": "Grass Wonder"
        },
        {
            "text": "……I understand. It's not often I get to take \na walk with Trainer-san, so let's go take a look.",
            "name": "Grass Wonder"
        },
        {
            "text": "As I thought, it's quite lively, isn't it～?",
            "name": "Grass Wonder"
        },
        {
            "text": "Trainer-san, what kind of game is this?",
            "name": "Grass Wonder"
        },
        {
            "text": "The game that Grass Wonder was curious about was a dance game."
        },
        {
            "text": "So it's a game you play by stepping on these buttons, \nit kind of seems a little bit like a Winning Live, doesn't it?",
            "name": "Grass Wonder",
            "choice_data_list": [
                "How about trying it!?"
            ]
        },
        {
            "text": "Eh? You mean…… me?",
            "name": "Grass Wonder"
        },
        {
            "text": "Hmmmm～…… well, I've done some dance training, \nso I should be able to play it……",
            "name": "Grass Wonder"
        },
        {
            "text": "Understood, I'll give it a try. \nDon't laugh if I'm not very good at it, okay?",
            "name": "Grass Wonder"
        },
        {
            "text": "And so, Grass Wonder started the game……"
        },
        {
            "text": "Hmm…… oh…… \nAh, ah……!?",
            "name": "Grass Wonder"
        },
        {
            "text": "…………",
            "name": "Grass Wonder",
            "choice_data_list": [
                "That looked a little hard",
                "That looked a little hard"
            ]
        },
        {
            "text": "……It didn't go anything like a Winning Live.",
            "name": "Grass Wonder"
        },
        {
            "text": "Ah, but it was an interesting game. \nIt's also a good work out.",
            "name": "Grass Wonder"
        },
        {
            "text": "So there are games like this, huh～? \nI learned about a lot of things today.",
            "name": "Grass Wonder"
        },
        {
            "text": "This was also because we took a walk together. \nTrainer-san, thank you very much for accompanying me.",
            "name": "Grass Wonder",
            "choice_data_list": [
                "You're welcome"
            ]
        },
        {
            "text": "When our schedules allow for it, let's take more walks together♪",
            "name": "Grass Wonder"
        },
        {
            "text": "Well then, I'll give it one more try……",
            "name": "Grass Wonder",
            "choice_data_list": [
                "Because it's a good work out, right?",
                "Because it's a good work out, right?"
            ]
        },
        {
            "text": "『To empathize is to know』…… to be able to understand without \nexchanging words, I'm in awe of your perceptiveness, Trainer-san.",
            "name": "Grass Wonder"
        },
        {
            "text": "Next I'll clear it, so just watch me.",
            "name": "Grass Wonder"
        },
        {
            "text": "Hmmmm～…… it's not going very well is it……?",
            "name": "Grass Wonder",
            "choice_data_list": [
                "Should we move on……?",
                "Should we move on……?"
            ]
        },
        {
            "text": "Oh, are you seriously asking that? \nI haven't excercised enough yet, you know?",
            "name": "Grass Wonder"
        },
        {
            "text": "And with that, I'll play another round, okay? \nThis is for excercise, after all～.",
            "name": "Grass Wonder"
        },
        {
            "text": "And so, the walk with Grass Wonder continued \nuntil she felt she could play the game well."
        }
    ]
}